utl_sphinx_theme/__init__.py
utl_sphinx_theme/layout.html
utl_sphinx_theme/theme.conf
utl_sphinx_theme/theme.toml
utl_sphinx_theme/static/logo.svg
utl_sphinx_theme/static/utl_sphinx_theme.css
utl_sphinx_theme-0.2.dist-info/METADATA
utl_sphinx_theme-0.2.dist-info/WHEEL
utl_sphinx_theme-0.2.dist-info/entry_points.txt
utl_sphinx_theme-0.2.dist-info/top_level.txt
utl_sphinx_theme-0.2.dist-info/RECORD
